{
  "source": "SOURATES",
  "total": 114,
  "items": [
    {
      "id": 1,
      "numero": 1,
      "nom_fr": "L'Ouverture",
      "nom_arabe": "الفاتحة",
      "translit": "Al-Fatiha",
      "nb_versets": 7,
      "lieu_revelation": "Mecque"
    },
    {
      "id": 2,
      "numero": 2,
      "nom_fr": "La Vache",
      "nom_arabe": "البقرة",
      "translit": "Al-Baqara",
      "nb_versets": 286,
      "lieu_revelation": "Médine"
    },
    {
      "id": 3,
      "numero": 3,
      "nom_fr": "La Famille d'Imran",
      "nom_arabe": "آل عمران",
      "translit": "Al-Imran",
      "nb_versets": 200,
      "lieu_revelation": "Médine"
    },
    {
      "id": 4,
      "numero": 4,
      "nom_fr": "Les Femmes",
      "nom_arabe": "النساء",
      "translit": "An-Nisa",
      "nb_versets": 176,
      "lieu_revelation": "Médine"
    },
    {
      "id": 5,
      "numero": 5,
      "nom_fr": "La Table Servie",
      "nom_arabe": "المائدة",
      "translit": "Al-Maida",
      "nb_versets": 120,
      "lieu_revelation": "Médine"
    },
    {
      "id": 6,
      "numero": 6,
      "nom_fr": "Les Bestiaux",
      "nom_arabe": "الأنعام",
      "translit": "Al-An'am",
      "nb_versets": 165,
      "lieu_revelation": "Mecque"
    },
    {
      "id": 7,
      "numero": 7,
      "nom_fr": "Les Murailles",
      "nom_arabe": "الأعراف",
      "translit": "Al-A'raf",
      "nb_versets": 206,
      "lieu_revelation": "Mecque"
    },
    {
      "id": 8,
      "numero": 8,
      "nom_fr": "Le Butin",
      "nom_arabe": "الأنفال",
      "translit": "Al-Anfal",
      "nb_versets": 75,
      "lieu_revelation": "Médine"
    },
    {
      "id": 9,
      "numero": 9,
      "nom_fr": "Le Repentir",
      "nom_arabe": "التوبة",
      "translit": "At-Tawba",
      "nb_versets": 129,
      "lieu_revelation": "Médine"
    },
    {
      "id": 10,
      "numero": 10,
      "nom_fr": "Jonas",
      "nom_arabe": "يونس",
      "translit": "Yunus",
      "nb_versets": 109,
      "lieu_revelation": "Mecque"
    },
    {
      "id": 11,
      "numero": 11,
      "nom_fr": "Houd",
      "nom_arabe": "هود",
      "translit": "Hud",
      "nb_versets": 123,
      "lieu_revelation": "Mecque"
    },
    {
      "id": 12,
      "numero": 12,
      "nom_fr": "Joseph",
      "nom_arabe": "يوسف",
      "translit": "Yusuf",
      "nb_versets": 111,
      "lieu_revelation": "Mecque"
    },
    {
      "id": 13,
      "numero": 13,
      "nom_fr": "Le Tonnerre",
      "nom_arabe": "الرعد",
      "translit": "Ar-Ra'd",
      "nb_versets": 43,
      "lieu_revelation": "Médine"
    },
    {
      "id": 14,
      "numero": 14,
      "nom_fr": "Abraham",
      "nom_arabe": "إبراهيم",
      "translit": "Ibrahim",
      "nb_versets": 52,
      "lieu_revelation": "Mecque"
    },
    {
      "id": 15,
      "numero": 15,
      "nom_fr": "Al-Hijr",
      "nom_arabe": "الحجر",
      "translit": "Al-Hijr",
      "nb_versets": 99,
      "lieu_revelation": "Mecque"
    },
    {
      "id": 16,
      "numero": 16,
      "nom_fr": "Les Abeilles",
      "nom_arabe": "النحل",
      "translit": "An-Nahl",
      "nb_versets": 128,
      "lieu_revelation": "Mecque"
    },
    {
      "id": 17,
      "numero": 17,
      "nom_fr": "Le Voyage Nocturne",
      "nom_arabe": "الإسراء",
      "translit": "Al-Isra",
      "nb_versets": 111,
      "lieu_revelation": "Mecque"
    },
    {
      "id": 18,
      "numero": 18,
      "nom_fr": "La Caverne",
      "nom_arabe": "الكهف",
      "translit": "Al-Kahf",
      "nb_versets": 110,
      "lieu_revelation": "Mecque"
    },
    {
      "id": 19,
      "numero": 19,
      "nom_fr": "Marie",
      "nom_arabe": "مريم",
      "translit": "Maryam",
      "nb_versets": 98,
      "lieu_revelation": "Mecque"
    },
    {
      "id": 20,
      "numero": 20,
      "nom_fr": "Ta-Ha",
      "nom_arabe": "طه",
      "translit": "Ta-Ha",
      "nb_versets": 135,
      "lieu_revelation": "Mecque"
    },
    {
      "id": 21,
      "numero": 21,
      "nom_fr": "Les Prophètes",
      "nom_arabe": "الأنبياء",
      "translit": "Al-Anbiya",
      "nb_versets": 112,
      "lieu_revelation": "Mecque"
    },
    {
      "id": 22,
      "numero": 22,
      "nom_fr": "Le Pèlerinage",
      "nom_arabe": "الحج",
      "translit": "Al-Hajj",
      "nb_versets": 78,
      "lieu_revelation": "Médine"
    },
    {
      "id": 23,
      "numero": 23,
      "nom_fr": "Les Croyants",
      "nom_arabe": "المؤمنون",
      "translit": "Al-Mu'minun",
      "nb_versets": 118,
      "lieu_revelation": "Mecque"
    },
    {
      "id": 24,
      "numero": 24,
      "nom_fr": "La Lumière",
      "nom_arabe": "النور",
      "translit": "An-Nur",
      "nb_versets": 64,
      "lieu_revelation": "Médine"
    },
    {
      "id": 25,
      "numero": 25,
      "nom_fr": "Le Discernement",
      "nom_arabe": "الفرقان",
      "translit": "Al-Furqan",
      "nb_versets": 77,
      "lieu_revelation": "Mecque"
    },
    {
      "id": 26,
      "numero": 26,
      "nom_fr": "Les Poètes",
      "nom_arabe": "الشعراء",
      "translit": "Ash-Shu'ara",
      "nb_versets": 227,
      "lieu_revelation": "Mecque"
    },
    {
      "id": 27,
      "numero": 27,
      "nom_fr": "Les Fourmis",
      "nom_arabe": "النمل",
      "translit": "An-Naml",
      "nb_versets": 93,
      "lieu_revelation": "Mecque"
    },
    {
      "id": 28,
      "numero": 28,
      "nom_fr": "Le Récit",
      "nom_arabe": "القصص",
      "translit": "Al-Qasas",
      "nb_versets": 88,
      "lieu_revelation": "Mecque"
    },
    {
      "id": 29,
      "numero": 29,
      "nom_fr": "L'Araignée",
      "nom_arabe": "العنكبوت",
      "translit": "Al-Ankabut",
      "nb_versets": 69,
      "lieu_revelation": "Mecque"
    },
    {
      "id": 30,
      "numero": 30,
      "nom_fr": "Les Romains",
      "nom_arabe": "الروم",
      "translit": "Ar-Rum",
      "nb_versets": 60,
      "lieu_revelation": "Mecque"
    },
    {
      "id": 31,
      "numero": 31,
      "nom_fr": "Luqman",
      "nom_arabe": "لقمان",
      "translit": "Luqman",
      "nb_versets": 34,
      "lieu_revelation": "Mecque"
    },
    {
      "id": 32,
      "numero": 32,
      "nom_fr": "La Prosternation",
      "nom_arabe": "السجدة",
      "translit": "As-Sajda",
      "nb_versets": 30,
      "lieu_revelation": "Mecque"
    },
    {
      "id": 33,
      "numero": 33,
      "nom_fr": "Les Coalisés",
      "nom_arabe": "الأحزاب",
      "translit": "Al-Ahzab",
      "nb_versets": 73,
      "lieu_revelation": "Médine"
    },
    {
      "id": 34,
      "numero": 34,
      "nom_fr": "Saba",
      "nom_arabe": "سبأ",
      "translit": "Saba",
      "nb_versets": 54,
      "lieu_revelation": "Mecque"
    },
    {
      "id": 35,
      "numero": 35,
      "nom_fr": "Le Créateur",
      "nom_arabe": "فاطر",
      "translit": "Fatir",
      "nb_versets": 45,
      "lieu_revelation": "Mecque"
    },
    {
      "id": 36,
      "numero": 36,
      "nom_fr": "Ya-Sin",
      "nom_arabe": "يس",
      "translit": "Ya-Sin",
      "nb_versets": 83,
      "lieu_revelation": "Mecque"
    },
    {
      "id": 37,
      "numero": 37,
      "nom_fr": "Les Rangés",
      "nom_arabe": "الصافات",
      "translit": "As-Saffat",
      "nb_versets": 182,
      "lieu_revelation": "Mecque"
    },
    {
      "id": 38,
      "numero": 38,
      "nom_fr": "Sad",
      "nom_arabe": "ص",
      "translit": "Sad",
      "nb_versets": 88,
      "lieu_revelation": "Mecque"
    },
    {
      "id": 39,
      "numero": 39,
      "nom_fr": "Les Groupes",
      "nom_arabe": "الزمر",
      "translit": "Az-Zumar",
      "nb_versets": 75,
      "lieu_revelation": "Mecque"
    },
    {
      "id": 40,
      "numero": 40,
      "nom_fr": "Le Pardonneur",
      "nom_arabe": "غافر",
      "translit": "Ghafir",
      "nb_versets": 85,
      "lieu_revelation": "Mecque"
    },
    {
      "id": 41,
      "numero": 41,
      "nom_fr": "Exposées en Détail",
      "nom_arabe": "فصلت",
      "translit": "Fussilat",
      "nb_versets": 54,
      "lieu_revelation": "Mecque"
    },
    {
      "id": 42,
      "numero": 42,
      "nom_fr": "La Consultation",
      "nom_arabe": "الشورى",
      "translit": "Ash-Shura",
      "nb_versets": 53,
      "lieu_revelation": "Mecque"
    },
    {
      "id": 43,
      "numero": 43,
      "nom_fr": "Les Ornements",
      "nom_arabe": "الزخرف",
      "translit": "Az-Zukhruf",
      "nb_versets": 89,
      "lieu_revelation": "Mecque"
    },
    {
      "id": 44,
      "numero": 44,
      "nom_fr": "La Fumée",
      "nom_arabe": "الدخان",
      "translit": "Ad-Dukhan",
      "nb_versets": 59,
      "lieu_revelation": "Mecque"
    },
    {
      "id": 45,
      "numero": 45,
      "nom_fr": "L'Agenouillée",
      "nom_arabe": "الجاثية",
      "translit": "Al-Jathiya",
      "nb_versets": 37,
      "lieu_revelation": "Mecque"
    },
    {
      "id": 46,
      "numero": 46,
      "nom_fr": "Les Dunes",
      "nom_arabe": "الأحقاف",
      "translit": "Al-Ahqaf",
      "nb_versets": 35,
      "lieu_revelation": "Mecque"
    },
    {
      "id": 47,
      "numero": 47,
      "nom_fr": "Muhammad",
      "nom_arabe": "محمد",
      "translit": "Muhammad",
      "nb_versets": 38,
      "lieu_revelation": "Médine"
    },
    {
      "id": 48,
      "numero": 48,
      "nom_fr": "La Victoire",
      "nom_arabe": "الفتح",
      "translit": "Al-Fath",
      "nb_versets": 29,
      "lieu_revelation": "Médine"
    },
    {
      "id": 49,
      "numero": 49,
      "nom_fr": "Les Appartements",
      "nom_arabe": "الحجرات",
      "translit": "Al-Hujurat",
      "nb_versets": 18,
      "lieu_revelation": "Médine"
    },
    {
      "id": 50,
      "numero": 50,
      "nom_fr": "Qaf",
      "nom_arabe": "ق",
      "translit": "Qaf",
      "nb_versets": 45,
      "lieu_revelation": "Mecque"
    },
    {
      "id": 51,
      "numero": 51,
      "nom_fr": "Les Vents",
      "nom_arabe": "الذاريات",
      "translit": "Adh-Dhariyat",
      "nb_versets": 60,
      "lieu_revelation": "Mecque"
    },
    {
      "id": 52,
      "numero": 52,
      "nom_fr": "Le Mont Sinaï",
      "nom_arabe": "الطور",
      "translit": "At-Tur",
      "nb_versets": 49,
      "lieu_revelation": "Mecque"
    },
    {
      "id": 53,
      "numero": 53,
      "nom_fr": "L'Étoile",
      "nom_arabe": "النجم",
      "translit": "An-Najm",
      "nb_versets": 62,
      "lieu_revelation": "Mecque"
    },
    {
      "id": 54,
      "numero": 54,
      "nom_fr": "La Lune",
      "nom_arabe": "القمر",
      "translit": "Al-Qamar",
      "nb_versets": 55,
      "lieu_revelation": "Mecque"
    },
    {
      "id": 55,
      "numero": 55,
      "nom_fr": "Le Tout Miséricordieux",
      "nom_arabe": "الرحمن",
      "translit": "Ar-Rahman",
      "nb_versets": 78,
      "lieu_revelation": "Mecque"
    },
    {
      "id": 56,
      "numero": 56,
      "nom_fr": "L'Événement",
      "nom_arabe": "الواقعة",
      "translit": "Al-Waqi'a",
      "nb_versets": 96,
      "lieu_revelation": "Mecque"
    },
    {
      "id": 57,
      "numero": 57,
      "nom_fr": "Le Fer",
      "nom_arabe": "الحديد",
      "translit": "Al-Hadid",
      "nb_versets": 29,
      "lieu_revelation": "Médine"
    },
    {
      "id": 58,
      "numero": 58,
      "nom_fr": "La Femme qui Dispute",
      "nom_arabe": "المجادلة",
      "translit": "Al-Mujadila",
      "nb_versets": 22,
      "lieu_revelation": "Médine"
    },
    {
      "id": 59,
      "numero": 59,
      "nom_fr": "L'Exode",
      "nom_arabe": "الحشر",
      "translit": "Al-Hashr",
      "nb_versets": 24,
      "lieu_revelation": "Médine"
    },
    {
      "id": 60,
      "numero": 60,
      "nom_fr": "La Femme Éprouvée",
      "nom_arabe": "الممتحنة",
      "translit": "Al-Mumtahana",
      "nb_versets": 13,
      "lieu_revelation": "Médine"
    },
    {
      "id": 61,
      "numero": 61,
      "nom_fr": "Le Rang",
      "nom_arabe": "الصف",
      "translit": "As-Saf",
      "nb_versets": 14,
      "lieu_revelation": "Médine"
    },
    {
      "id": 62,
      "numero": 62,
      "nom_fr": "Le Vendredi",
      "nom_arabe": "الجمعة",
      "translit": "Al-Jumu'a",
      "nb_versets": 11,
      "lieu_revelation": "Médine"
    },
    {
      "id": 63,
      "numero": 63,
      "nom_fr": "Les Hypocrites",
      "nom_arabe": "المنافقون",
      "translit": "Al-Munafiqun",
      "nb_versets": 11,
      "lieu_revelation": "Médine"
    },
    {
      "id": 64,
      "numero": 64,
      "nom_fr": "La Spoliation",
      "nom_arabe": "التغابن",
      "translit": "At-Taghabun",
      "nb_versets": 18,
      "lieu_revelation": "Médine"
    },
    {
      "id": 65,
      "numero": 65,
      "nom_fr": "Le Divorce",
      "nom_arabe": "الطلاق",
      "translit": "At-Talaq",
      "nb_versets": 12,
      "lieu_revelation": "Médine"
    },
    {
      "id": 66,
      "numero": 66,
      "nom_fr": "L'Interdiction",
      "nom_arabe": "التحريم",
      "translit": "At-Tahrim",
      "nb_versets": 12,
      "lieu_revelation": "Médine"
    },
    {
      "id": 67,
      "numero": 67,
      "nom_fr": "La Royauté",
      "nom_arabe": "الملك",
      "translit": "Al-Mulk",
      "nb_versets": 30,
      "lieu_revelation": "Mecque"
    },
    {
      "id": 68,
      "numero": 68,
      "nom_fr": "Le Calame",
      "nom_arabe": "القلم",
      "translit": "Al-Qalam",
      "nb_versets": 52,
      "lieu_revelation": "Mecque"
    },
    {
      "id": 69,
      "numero": 69,
      "nom_fr": "L'Inévitable",
      "nom_arabe": "الحاقة",
      "translit": "Al-Haqqa",
      "nb_versets": 52,
      "lieu_revelation": "Mecque"
    },
    {
      "id": 70,
      "numero": 70,
      "nom_fr": "Les Degrés",
      "nom_arabe": "المعارج",
      "translit": "Al-Ma'arij",
      "nb_versets": 44,
      "lieu_revelation": "Mecque"
    },
    {
      "id": 71,
      "numero": 71,
      "nom_fr": "Noé",
      "nom_arabe": "نوح",
      "translit": "Nuh",
      "nb_versets": 28,
      "lieu_revelation": "Mecque"
    },
    {
      "id": 72,
      "numero": 72,
      "nom_fr": "Les Djinns",
      "nom_arabe": "الجن",
      "translit": "Al-Jinn",
      "nb_versets": 28,
      "lieu_revelation": "Mecque"
    },
    {
      "id": 73,
      "numero": 73,
      "nom_fr": "L'Enveloppé",
      "nom_arabe": "المزمل",
      "translit": "Al-Muzzammil",
      "nb_versets": 20,
      "lieu_revelation": "Mecque"
    },
    {
      "id": 74,
      "numero": 74,
      "nom_fr": "Le Revêtu",
      "nom_arabe": "المدثر",
      "translit": "Al-Muddaththir",
      "nb_versets": 56,
      "lieu_revelation": "Mecque"
    },
    {
      "id": 75,
      "numero": 75,
      "nom_fr": "La Résurrection",
      "nom_arabe": "القيامة",
      "translit": "Al-Qiyama",
      "nb_versets": 40,
      "lieu_revelation": "Mecque"
    },
    {
      "id": 76,
      "numero": 76,
      "nom_fr": "L'Homme",
      "nom_arabe": "الإنسان",
      "translit": "Al-Insan",
      "nb_versets": 31,
      "lieu_revelation": "Mecque"
    },
    {
      "id": 77,
      "numero": 77,
      "nom_fr": "Les Envoyés",
      "nom_arabe": "المرسلات",
      "translit": "Al-Mursalat",
      "nb_versets": 50,
      "lieu_revelation": "Mecque"
    },
    {
      "id": 78,
      "numero": 78,
      "nom_fr": "La Nouvelle",
      "nom_arabe": "النبأ",
      "translit": "An-Naba",
      "nb_versets": 40,
      "lieu_revelation": "Mecque"
    },
    {
      "id": 79,
      "numero": 79,
      "nom_fr": "Ceux qui Arrachent",
      "nom_arabe": "النازعات",
      "translit": "An-Nazi'at",
      "nb_versets": 46,
      "lieu_revelation": "Mecque"
    },
    {
      "id": 80,
      "numero": 80,
      "nom_fr": "Il a Froncé les Sourcils",
      "nom_arabe": "عبس",
      "translit": "Abasa",
      "nb_versets": 42,
      "lieu_revelation": "Mecque"
    },
    {
      "id": 81,
      "numero": 81,
      "nom_fr": "L'Enroulement",
      "nom_arabe": "التكوير",
      "translit": "At-Takwir",
      "nb_versets": 29,
      "lieu_revelation": "Mecque"
    },
    {
      "id": 82,
      "numero": 82,
      "nom_fr": "La Déchirure",
      "nom_arabe": "الانفطار",
      "translit": "Al-Infitar",
      "nb_versets": 19,
      "lieu_revelation": "Mecque"
    },
    {
      "id": 83,
      "numero": 83,
      "nom_fr": "Les Fraudeurs",
      "nom_arabe": "المطففين",
      "translit": "Al-Mutaffifin",
      "nb_versets": 36,
      "lieu_revelation": "Mecque"
    },
    {
      "id": 84,
      "numero": 84,
      "nom_fr": "La Fissure",
      "nom_arabe": "الانشقاق",
      "translit": "Al-Inshiqaq",
      "nb_versets": 25,
      "lieu_revelation": "Mecque"
    },
    {
      "id": 85,
      "numero": 85,
      "nom_fr": "Les Constellations",
      "nom_arabe": "البروج",
      "translit": "Al-Buruj",
      "nb_versets": 22,
      "lieu_revelation": "Mecque"
    },
    {
      "id": 86,
      "numero": 86,
      "nom_fr": "L'Astre Nocturne",
      "nom_arabe": "الطارق",
      "translit": "At-Tariq",
      "nb_versets": 17,
      "lieu_revelation": "Mecque"
    },
    {
      "id": 87,
      "numero": 87,
      "nom_fr": "Le Très-Haut",
      "nom_arabe": "الأعلى",
      "translit": "Al-A'la",
      "nb_versets": 19,
      "lieu_revelation": "Mecque"
    },
    {
      "id": 88,
      "numero": 88,
      "nom_fr": "L'Enveloppante",
      "nom_arabe": "الغاشية",
      "translit": "Al-Ghashiya",
      "nb_versets": 26,
      "lieu_revelation": "Mecque"
    },
    {
      "id": 89,
      "numero": 89,
      "nom_fr": "L'Aube",
      "nom_arabe": "الفجر",
      "translit": "Al-Fajr",
      "nb_versets": 30,
      "lieu_revelation": "Mecque"
    },
    {
      "id": 90,
      "numero": 90,
      "nom_fr": "La Cité",
      "nom_arabe": "البلد",
      "translit": "Al-Balad",
      "nb_versets": 20,
      "lieu_revelation": "Mecque"
    },
    {
      "id": 91,
      "numero": 91,
      "nom_fr": "Le Soleil",
      "nom_arabe": "الشمس",
      "translit": "Ash-Shams",
      "nb_versets": 15,
      "lieu_revelation": "Mecque"
    },
    {
      "id": 92,
      "numero": 92,
      "nom_fr": "La Nuit",
      "nom_arabe": "الليل",
      "translit": "Al-Layl",
      "nb_versets": 21,
      "lieu_revelation": "Mecque"
    },
    {
      "id": 93,
      "numero": 93,
      "nom_fr": "La Matinée",
      "nom_arabe": "الضحى",
      "translit": "Ad-Duha",
      "nb_versets": 11,
      "lieu_revelation": "Mecque"
    },
    {
      "id": 94,
      "numero": 94,
      "nom_fr": "L'Ouverture de la Poitrine",
      "nom_arabe": "الشرح",
      "translit": "Ash-Sharh",
      "nb_versets": 8,
      "lieu_revelation": "Mecque"
    },
    {
      "id": 95,
      "numero": 95,
      "nom_fr": "Le Figuier",
      "nom_arabe": "التين",
      "translit": "At-Tin",
      "nb_versets": 8,
      "lieu_revelation": "Mecque"
    },
    {
      "id": 96,
      "numero": 96,
      "nom_fr": "Le Caillot de Sang",
      "nom_arabe": "العلق",
      "translit": "Al-Alaq",
      "nb_versets": 19,
      "lieu_revelation": "Mecque"
    },
    {
      "id": 97,
      "numero": 97,
      "nom_fr": "La Nuit du Destin",
      "nom_arabe": "القدر",
      "translit": "Al-Qadr",
      "nb_versets": 5,
      "lieu_revelation": "Mecque"
    },
    {
      "id": 98,
      "numero": 98,
      "nom_fr": "La Preuve",
      "nom_arabe": "البينة",
      "translit": "Al-Bayyina",
      "nb_versets": 8,
      "lieu_revelation": "Médine"
    },
    {
      "id": 99,
      "numero": 99,
      "nom_fr": "Le Séisme",
      "nom_arabe": "الزلزلة",
      "translit": "Az-Zalzala",
      "nb_versets": 8,
      "lieu_revelation": "Médine"
    },
    {
      "id": 100,
      "numero": 100,
      "nom_fr": "Les Coursiers",
      "nom_arabe": "العاديات",
      "translit": "Al-Adiyat",
      "nb_versets": 11,
      "lieu_revelation": "Mecque"
    },
    {
      "id": 101,
      "numero": 101,
      "nom_fr": "Le Fracas",
      "nom_arabe": "القارعة",
      "translit": "Al-Qari'a",
      "nb_versets": 11,
      "lieu_revelation": "Mecque"
    },
    {
      "id": 102,
      "numero": 102,
      "nom_fr": "La Course aux Richesses",
      "nom_arabe": "التكاثر",
      "translit": "At-Takathur",
      "nb_versets": 8,
      "lieu_revelation": "Mecque"
    },
    {
      "id": 103,
      "numero": 103,
      "nom_fr": "Le Temps",
      "nom_arabe": "العصر",
      "translit": "Al-Asr",
      "nb_versets": 3,
      "lieu_revelation": "Mecque"
    },
    {
      "id": 104,
      "numero": 104,
      "nom_fr": "Le Calomniateur",
      "nom_arabe": "الهمزة",
      "translit": "Al-Humaza",
      "nb_versets": 9,
      "lieu_revelation": "Mecque"
    },
    {
      "id": 105,
      "numero": 105,
      "nom_fr": "L'Éléphant",
      "nom_arabe": "الفيل",
      "translit": "Al-Fil",
      "nb_versets": 5,
      "lieu_revelation": "Mecque"
    },
    {
      "id": 106,
      "numero": 106,
      "nom_fr": "Quraysh",
      "nom_arabe": "قريش",
      "translit": "Quraysh",
      "nb_versets": 4,
      "lieu_revelation": "Mecque"
    },
    {
      "id": 107,
      "numero": 107,
      "nom_fr": "Les Ustensiles",
      "nom_arabe": "الماعون",
      "translit": "Al-Ma'un",
      "nb_versets": 7,
      "lieu_revelation": "Mecque"
    },
    {
      "id": 108,
      "numero": 108,
      "nom_fr": "L'Abondance",
      "nom_arabe": "الكوثر",
      "translit": "Al-Kawthar",
      "nb_versets": 3,
      "lieu_revelation": "Mecque"
    },
    {
      "id": 109,
      "numero": 109,
      "nom_fr": "Les Infidèles",
      "nom_arabe": "الكافرون",
      "translit": "Al-Kafirun",
      "nb_versets": 6,
      "lieu_revelation": "Mecque"
    },
    {
      "id": 110,
      "numero": 110,
      "nom_fr": "Le Secours",
      "nom_arabe": "النصر",
      "translit": "An-Nasr",
      "nb_versets": 3,
      "lieu_revelation": "Médine"
    },
    {
      "id": 111,
      "numero": 111,
      "nom_fr": "Les Fibres",
      "nom_arabe": "المسد",
      "translit": "Al-Masad",
      "nb_versets": 5,
      "lieu_revelation": "Mecque"
    },
    {
      "id": 112,
      "numero": 112,
      "nom_fr": "Le Monothéisme Pur",
      "nom_arabe": "الإخلاص",
      "translit": "Al-Ikhlas",
      "nb_versets": 4,
      "lieu_revelation": "Mecque"
    },
    {
      "id": 113,
      "numero": 113,
      "nom_fr": "L'Aube Naissante",
      "nom_arabe": "الفلق",
      "translit": "Al-Falaq",
      "nb_versets": 5,
      "lieu_revelation": "Mecque"
    },
    {
      "id": 114,
      "numero": 114,
      "nom_fr": "Les Hommes",
      "nom_arabe": "الناس",
      "translit": "An-Nas",
      "nb_versets": 6,
      "lieu_revelation": "Mecque"
    }
  ]
}